setup.py
modulo/__init__.py
modulo/connection.py
modulo/modulos.py
modulo/scripts.py
modulo_python.egg-info/PKG-INFO
modulo_python.egg-info/SOURCES.txt
modulo_python.egg-info/dependency_links.txt
modulo_python.egg-info/entry_points.txt
modulo_python.egg-info/requires.txt
modulo_python.egg-info/top_level.txt