Metadata-Version: 1.1
Name: modulo-python
Version: 1.1
Summary: Python support for Modulo hardware
Home-page: https://github.com/integer-labs/modulo-python
Author: Erin Tomson
Author-email: erin@integerlabs.net
License: UNKNOWN
Download-URL: https://github.com/integer-labs/modulo-python/tarball/0.1
Platform: UNKNOWN
